aiovk_new/__init__.py
aiovk_new/api.py
aiovk_new/audio/__init__.py
aiovk_new/audio/get.py
aiovk_new/audio/search.py
aiovk_new/base.py
aiovk_new/models/attachments/__init__.py
aiovk_new/models/attachments/link.py
aiovk_new/models/attachments/photo.py
aiovk_new/models/attachments/size.py
aiovk_new/models/post.py
aiovk_new/models/song.py
aiovk_new/wall/__init__.py
aiovk_new/wall/get.py
aiovk_new-0.0.1.dist-info/LICENSE
aiovk_new-0.0.1.dist-info/WHEEL
aiovk_new-0.0.1.dist-info/METADATA
aiovk_new-0.0.1.dist-info/RECORD
